gwtransport1d/__init__.py
gwtransport1d/advection.py
gwtransport1d/deposition.py
gwtransport1d/diffusion.py
gwtransport1d/gamma.py
gwtransport1d/logremoval.py
gwtransport1d/residence_time.py
gwtransport1d/utils.py
gwtransport1d-0.8.0.dist-info/METADATA
gwtransport1d-0.8.0.dist-info/WHEEL
gwtransport1d-0.8.0.dist-info/licenses/LICENSE
gwtransport1d-0.8.0.dist-info/RECORD
