Metadata-Version: 2.4
Name: gwtransport1d
Version: 0.8.0
Summary: Transport of contaminants in 1D groundwater flow system
Project-URL: Homepage, https://github.com/bdestombe/python_gwtransport1d
Author-email: Bas des Tombe <bdestombe@gmail.com>
License:                     GNU AFFERO GENERAL PUBLIC LICENSE
License-File: LICENSE
Keywords: 1D,deposition,groundwater,transport
Classifier: Programming Language :: Python :: 3.10
Classifier: Programming Language :: Python :: 3.11
Classifier: Programming Language :: Python :: 3.12
Requires-Python: >=3.10
Requires-Dist: matplotlib
Requires-Dist: numpy
Requires-Dist: pandas
Requires-Dist: scipy
Provides-Extra: test
Requires-Dist: pytest; extra == 'test'
Requires-Dist: pytest-cov; extra == 'test'
Requires-Dist: pytest-xdist; extra == 'test'
Requires-Dist: ruff==0.11.0; extra == 'test'
Requires-Dist: validate-pyproject[all,store]; extra == 'test'
